calc_plus/__init__.py
calc_plus/other.py
calc_plus/percent.py
calc_plus-1.0.dist-info/METADATA
calc_plus-1.0.dist-info/WHEEL
calc_plus-1.0.dist-info/top_level.txt
calc_plus-1.0.dist-info/RECORD
