Metadata-Version: 2.1
Name: calc-plus
Version: 1.0
Summary: Other convenience functions
Home-page: https://github.com/keegang6705/calc_plus
Author: keegang_6705
Author-email: darunphobwi@gmail.com
License: MIT
Platform: UNKNOWN
Requires-Python: >=3.0
